<?xml version="1.0" encoding="UTF-8"?>

  <extension type="package" version="3.0" method="upgrade">
    <name>Taekwondo Club</name>
    <author>Markus Moser</author>
    <creationDate>February 2019</creationDate>
    <packagename>tkdclub</packagename>
    <version>3.1.0</version>
    <url>http://www.taekwondo-uttendorf.at</url>
    <packager>Markus Moser</packager>
    <packagerurl>http://www.taekwondo-uttendorf.at</packagerurl>
    <description>Package for tkdclub extension</description>
    <update></update>
    <files folder="packages">
      <file type="component" id="com_tkdclub">com_tkdclub.zip</file>
      <file type="plugin" id="tkdclublogo" group="quickicon">plg_quickicon_tkdclublogo.zip</file>
      <file type="plugin" id="tkdclubgrade" group="content">plg_content_tkdclubgrade.zip</file>
      <file type="file" id="tkdclubfile">cli_tkdclubfile.zip</file>
    </files>
  </extension>